[
  {
    "url": "https://sctech.qzz.io",
    "status": "up",
    "timestamp": "2026-03-19T00:57:54.183990"
  },
  {
    "url": "https://blog.sctech.qzz.io",
    "status": "up",
    "timestamp": "2026-03-19T00:57:59.002406"
  },
  {
    "url": "https://docs.sctech.qzz.io",
    "status": "up",
    "timestamp": "2026-03-19T00:58:05.244995"
  },
  {
    "url": "https://go.sctech.localplayer.dev",
    "status": "down",
    "timestamp": "2026-03-19T00:58:05.630452"
  },
  {
    "url": "https://cndl.web.app",
    "status": "up",
    "timestamp": "2026-03-19T00:58:05.831986"
  },
  {
    "url": "https://osearch.sctech.qzz.io",
    "status": "up",
    "timestamp": "2026-03-19T00:58:06.588319"
  },
  {
    "url": "https://lolchat.app.sctech.localplayer.dev",
    "status": "up",
    "timestamp": "2026-03-19T00:58:07.179157"
  },
  {
    "url": "https://markdown.sctech.qzz.io",
    "status": "up",
    "timestamp": "2026-03-19T00:58:11.921069"
  },
  {
    "url": "https://breadblog.sctech.qzz.io",
    "status": "up",
    "timestamp": "2026-03-19T00:58:12.115597"
  },
  {
    "url": "https://wwwterminal.sctech.qzz.io",
    "status": "up",
    "timestamp": "2026-03-19T00:58:12.936218"
  },
  {
    "url": "https://nnn.n.nu",
    "status": "down",
    "timestamp": "2026-03-19T00:58:13.318244"
  }
]