[
  {
    "url": "https://sctech.qzz.io",
    "status": "down",
    "timestamp": "2026-07-17T10:28:55.803359"
  },
  {
    "url": "https://blog.sctech.qzz.io",
    "status": "up",
    "timestamp": "2026-07-17T10:28:56.068502"
  },
  {
    "url": "https://docs.sctech.qzz.io",
    "status": "up",
    "timestamp": "2026-07-17T10:28:56.450431"
  },
  {
    "url": "https://go.sctech.localplayer.dev",
    "status": "down",
    "timestamp": "2026-07-17T10:28:56.864584"
  },
  {
    "url": "https://cndl.web.app",
    "status": "up",
    "timestamp": "2026-07-17T10:28:57.022291"
  },
  {
    "url": "https://osearch.sctech.qzz.io",
    "status": "up",
    "timestamp": "2026-07-17T10:28:57.778835"
  },
  {
    "url": "https://lolchat.app.sctech.localplayer.dev",
    "status": "up",
    "timestamp": "2026-07-17T10:28:58.435495"
  },
  {
    "url": "https://markdown.sctech.qzz.io",
    "status": "up",
    "timestamp": "2026-07-17T10:28:59.129789"
  },
  {
    "url": "https://breadblog.sctech.qzz.io",
    "status": "up",
    "timestamp": "2026-07-17T10:28:59.839463"
  },
  {
    "url": "https://wwwterminal.sctech.qzz.io",
    "status": "up",
    "timestamp": "2026-07-17T10:29:00.521559"
  },
  {
    "url": "https://nnn.n.nu",
    "status": "down",
    "timestamp": "2026-07-17T10:29:00.807603"
  }
]