[
  {
    "url": "https://sctech.qzz.io",
    "status": "up",
    "timestamp": "2025-10-26T15:59:06.174843"
  },
  {
    "url": "https://blog.sctech.qzz.io",
    "status": "up",
    "timestamp": "2025-10-26T15:59:09.945969"
  },
  {
    "url": "https://docs.sctech.qzz.io",
    "status": "up",
    "timestamp": "2025-10-26T15:59:10.553155"
  },
  {
    "url": "https://go.sctech.localplayer.dev",
    "status": "up",
    "timestamp": "2025-10-26T15:59:11.187140"
  },
  {
    "url": "https://cndl.web.app",
    "status": "up",
    "timestamp": "2025-10-26T15:59:11.299876"
  },
  {
    "url": "https://osearch.sctech.qzz.io",
    "status": "up",
    "timestamp": "2025-10-26T15:59:15.501359"
  },
  {
    "url": "https://lolchat.app.sctech.localplayer.dev",
    "status": "up",
    "timestamp": "2025-10-26T15:59:15.677939"
  },
  {
    "url": "https://markdown.sctech.qzz.io",
    "status": "up",
    "timestamp": "2025-10-26T15:59:24.094663"
  },
  {
    "url": "https://breadblog.sctech.qzz.io",
    "status": "up",
    "timestamp": "2025-10-26T15:59:24.481034"
  },
  {
    "url": "https://wwwterminal.sctech.qzz.io",
    "status": "up",
    "timestamp": "2025-10-26T15:59:28.813426"
  },
  {
    "url": "https://nnn.n.nu",
    "status": "up",
    "timestamp": "2025-10-26T15:59:29.242786"
  }
]