[
  {
    "url": "https://sctech.qzz.io",
    "status": "up",
    "timestamp": "2026-04-14T14:10:38.248780"
  },
  {
    "url": "https://blog.sctech.qzz.io",
    "status": "up",
    "timestamp": "2026-04-14T14:10:38.643593"
  },
  {
    "url": "https://docs.sctech.qzz.io",
    "status": "up",
    "timestamp": "2026-04-14T14:10:41.135045"
  },
  {
    "url": "https://go.sctech.localplayer.dev",
    "status": "down",
    "timestamp": "2026-04-14T14:10:41.509603"
  },
  {
    "url": "https://cndl.web.app",
    "status": "up",
    "timestamp": "2026-04-14T14:10:41.595981"
  },
  {
    "url": "https://osearch.sctech.qzz.io",
    "status": "up",
    "timestamp": "2026-04-14T14:10:45.213608"
  },
  {
    "url": "https://lolchat.app.sctech.localplayer.dev",
    "status": "up",
    "timestamp": "2026-04-14T14:10:45.803977"
  },
  {
    "url": "https://markdown.sctech.qzz.io",
    "status": "up",
    "timestamp": "2026-04-14T14:10:46.338498"
  },
  {
    "url": "https://breadblog.sctech.qzz.io",
    "status": "up",
    "timestamp": "2026-04-14T14:10:47.303266"
  },
  {
    "url": "https://wwwterminal.sctech.qzz.io",
    "status": "up",
    "timestamp": "2026-04-14T14:10:48.402121"
  },
  {
    "url": "https://nnn.n.nu",
    "status": "down",
    "timestamp": "2026-04-14T14:10:48.866906"
  }
]