[
  {
    "url": "https://sctech.qzz.io",
    "status": "up",
    "timestamp": "2026-01-11T15:24:26.191763"
  },
  {
    "url": "https://blog.sctech.qzz.io",
    "status": "up",
    "timestamp": "2026-01-11T15:24:27.224258"
  },
  {
    "url": "https://docs.sctech.qzz.io",
    "status": "up",
    "timestamp": "2026-01-11T15:24:37.689578"
  },
  {
    "url": "https://go.sctech.localplayer.dev",
    "status": "down",
    "timestamp": "2026-01-11T15:24:38.101088"
  },
  {
    "url": "https://cndl.web.app",
    "status": "up",
    "timestamp": "2026-01-11T15:24:38.241787"
  },
  {
    "url": "https://osearch.sctech.qzz.io",
    "status": "up",
    "timestamp": "2026-01-11T15:24:42.772699"
  },
  {
    "url": "https://lolchat.app.sctech.localplayer.dev",
    "status": "up",
    "timestamp": "2026-01-11T15:24:43.266132"
  },
  {
    "url": "https://markdown.sctech.qzz.io",
    "status": "up",
    "timestamp": "2026-01-11T15:24:43.495276"
  },
  {
    "url": "https://breadblog.sctech.qzz.io",
    "status": "up",
    "timestamp": "2026-01-11T15:24:44.377308"
  },
  {
    "url": "https://wwwterminal.sctech.qzz.io",
    "status": "up",
    "timestamp": "2026-01-11T15:24:44.594877"
  },
  {
    "url": "https://nnn.n.nu",
    "status": "down",
    "timestamp": "2026-01-11T15:24:45.197739"
  }
]