[
  {
    "url": "https://sctech.localplayer.dev",
    "status": "up",
    "timestamp": "2025-10-05T03:28:19.093650"
  },
  {
    "url": "https://blog.sctech.localplayer.dev",
    "status": "up",
    "timestamp": "2025-10-05T03:28:19.272174"
  },
  {
    "url": "https://docs.sctech.localplayer.dev",
    "status": "up",
    "timestamp": "2025-10-05T03:28:19.659617"
  },
  {
    "url": "https://go.sctech.localplayer.dev",
    "status": "up",
    "timestamp": "2025-10-05T03:28:20.392399"
  },
  {
    "url": "https://cndl.web.app",
    "status": "up",
    "timestamp": "2025-10-05T03:28:20.531483"
  },
  {
    "url": "https://osearch.app.sctech.localplayer.dev",
    "status": "up",
    "timestamp": "2025-10-05T03:28:21.020354"
  },
  {
    "url": "https://lolchat.app.sctech.localplayer.dev",
    "status": "up",
    "timestamp": "2025-10-05T03:28:21.516295"
  },
  {
    "url": "https://go-md.app.sctech.localplayer.dev",
    "status": "up",
    "timestamp": "2025-10-05T03:28:22.025180"
  },
  {
    "url": "https://breadblog.app.sctech.localplayer.dev",
    "status": "up",
    "timestamp": "2025-10-05T03:28:22.141094"
  },
  {
    "url": "https://wwwterminal.app.sctech.localplayer.dev",
    "status": "up",
    "timestamp": "2025-10-05T03:28:22.629667"
  },
  {
    "url": "https://nnn.n.nu",
    "status": "up",
    "timestamp": "2025-10-05T03:28:23.036906"
  }
]