[
  {
    "url": "https://sctech.qzz.io",
    "status": "up",
    "timestamp": "2025-11-17T15:17:39.928198"
  },
  {
    "url": "https://blog.sctech.qzz.io",
    "status": "up",
    "timestamp": "2025-11-17T15:17:40.120957"
  },
  {
    "url": "https://docs.sctech.qzz.io",
    "status": "up",
    "timestamp": "2025-11-17T15:17:40.629144"
  },
  {
    "url": "https://go.sctech.localplayer.dev",
    "status": "up",
    "timestamp": "2025-11-17T15:17:41.249867"
  },
  {
    "url": "https://cndl.web.app",
    "status": "up",
    "timestamp": "2025-11-17T15:17:41.346419"
  },
  {
    "url": "https://osearch.sctech.qzz.io",
    "status": "up",
    "timestamp": "2025-11-17T15:17:46.838509"
  },
  {
    "url": "https://lolchat.app.sctech.localplayer.dev",
    "status": "up",
    "timestamp": "2025-11-17T15:17:47.381580"
  },
  {
    "url": "https://markdown.sctech.qzz.io",
    "status": "up",
    "timestamp": "2025-11-17T15:17:53.063561"
  },
  {
    "url": "https://breadblog.sctech.qzz.io",
    "status": "up",
    "timestamp": "2025-11-17T15:17:53.473140"
  },
  {
    "url": "https://wwwterminal.sctech.qzz.io",
    "status": "up",
    "timestamp": "2025-11-17T15:17:54.196072"
  },
  {
    "url": "https://nnn.n.nu",
    "status": "down",
    "timestamp": "2025-11-17T15:17:55.159944"
  }
]