[
  {
    "url": "https://sctech.qzz.io",
    "status": "up",
    "timestamp": "2026-01-30T23:57:54.834148"
  },
  {
    "url": "https://blog.sctech.qzz.io",
    "status": "up",
    "timestamp": "2026-01-30T23:57:55.226586"
  },
  {
    "url": "https://docs.sctech.qzz.io",
    "status": "up",
    "timestamp": "2026-01-30T23:57:55.438488"
  },
  {
    "url": "https://go.sctech.localplayer.dev",
    "status": "down",
    "timestamp": "2026-01-30T23:57:56.111751"
  },
  {
    "url": "https://cndl.web.app",
    "status": "up",
    "timestamp": "2026-01-30T23:57:56.218126"
  },
  {
    "url": "https://osearch.sctech.qzz.io",
    "status": "up",
    "timestamp": "2026-01-30T23:57:56.544131"
  },
  {
    "url": "https://lolchat.app.sctech.localplayer.dev",
    "status": "up",
    "timestamp": "2026-01-30T23:57:56.723159"
  },
  {
    "url": "https://markdown.sctech.qzz.io",
    "status": "up",
    "timestamp": "2026-01-30T23:58:01.888860"
  },
  {
    "url": "https://breadblog.sctech.qzz.io",
    "status": "up",
    "timestamp": "2026-01-30T23:58:07.204642"
  },
  {
    "url": "https://wwwterminal.sctech.qzz.io",
    "status": "up",
    "timestamp": "2026-01-30T23:58:10.623354"
  },
  {
    "url": "https://nnn.n.nu",
    "status": "down",
    "timestamp": "2026-01-30T23:58:11.018188"
  }
]