[
  {
    "url": "https://sctech.qzz.io",
    "status": "up",
    "timestamp": "2025-12-21T17:15:37.689867"
  },
  {
    "url": "https://blog.sctech.qzz.io",
    "status": "up",
    "timestamp": "2025-12-21T17:15:46.203772"
  },
  {
    "url": "https://docs.sctech.qzz.io",
    "status": "up",
    "timestamp": "2025-12-21T17:15:46.734157"
  },
  {
    "url": "https://go.sctech.localplayer.dev",
    "status": "down",
    "timestamp": "2025-12-21T17:15:47.565785"
  },
  {
    "url": "https://cndl.web.app",
    "status": "up",
    "timestamp": "2025-12-21T17:15:47.665273"
  },
  {
    "url": "https://osearch.sctech.qzz.io",
    "status": "up",
    "timestamp": "2025-12-21T17:15:48.669203"
  },
  {
    "url": "https://lolchat.app.sctech.localplayer.dev",
    "status": "up",
    "timestamp": "2025-12-21T17:15:49.171515"
  },
  {
    "url": "https://markdown.sctech.qzz.io",
    "status": "up",
    "timestamp": "2025-12-21T17:15:54.365914"
  },
  {
    "url": "https://breadblog.sctech.qzz.io",
    "status": "up",
    "timestamp": "2025-12-21T17:15:58.654754"
  },
  {
    "url": "https://wwwterminal.sctech.qzz.io",
    "status": "up",
    "timestamp": "2025-12-21T17:15:59.241094"
  },
  {
    "url": "https://nnn.n.nu",
    "status": "down",
    "timestamp": "2025-12-21T17:16:00.299153"
  }
]