[
  {
    "url": "https://sctech.qzz.io",
    "status": "up",
    "timestamp": "2025-12-09T17:19:53.078805"
  },
  {
    "url": "https://blog.sctech.qzz.io",
    "status": "up",
    "timestamp": "2025-12-09T17:19:53.662156"
  },
  {
    "url": "https://docs.sctech.qzz.io",
    "status": "up",
    "timestamp": "2025-12-09T17:20:07.541192"
  },
  {
    "url": "https://go.sctech.localplayer.dev",
    "status": "up",
    "timestamp": "2025-12-09T17:20:08.398634"
  },
  {
    "url": "https://cndl.web.app",
    "status": "up",
    "timestamp": "2025-12-09T17:20:08.611922"
  },
  {
    "url": "https://osearch.sctech.qzz.io",
    "status": "up",
    "timestamp": "2025-12-09T17:20:08.868898"
  },
  {
    "url": "https://lolchat.app.sctech.localplayer.dev",
    "status": "up",
    "timestamp": "2025-12-09T17:20:09.485079"
  },
  {
    "url": "https://markdown.sctech.qzz.io",
    "status": "up",
    "timestamp": "2025-12-09T17:20:15.065817"
  },
  {
    "url": "https://breadblog.sctech.qzz.io",
    "status": "up",
    "timestamp": "2025-12-09T17:20:20.068764"
  },
  {
    "url": "https://wwwterminal.sctech.qzz.io",
    "status": "up",
    "timestamp": "2025-12-09T17:20:25.497261"
  },
  {
    "url": "https://nnn.n.nu",
    "status": "down",
    "timestamp": "2025-12-09T17:20:26.047648"
  }
]