[
  {
    "url": "https://sctech.qzz.io",
    "status": "up",
    "timestamp": "2026-03-20T17:30:14.589941"
  },
  {
    "url": "https://blog.sctech.qzz.io",
    "status": "up",
    "timestamp": "2026-03-20T17:30:14.816392"
  },
  {
    "url": "https://docs.sctech.qzz.io",
    "status": "up",
    "timestamp": "2026-03-20T17:30:19.603704"
  },
  {
    "url": "https://go.sctech.localplayer.dev",
    "status": "down",
    "timestamp": "2026-03-20T17:30:20.146623"
  },
  {
    "url": "https://cndl.web.app",
    "status": "up",
    "timestamp": "2026-03-20T17:30:20.202532"
  },
  {
    "url": "https://osearch.sctech.qzz.io",
    "status": "up",
    "timestamp": "2026-03-20T17:30:20.905025"
  },
  {
    "url": "https://lolchat.app.sctech.localplayer.dev",
    "status": "up",
    "timestamp": "2026-03-20T17:30:21.510417"
  },
  {
    "url": "https://markdown.sctech.qzz.io",
    "status": "up",
    "timestamp": "2026-03-20T17:30:22.416981"
  },
  {
    "url": "https://breadblog.sctech.qzz.io",
    "status": "up",
    "timestamp": "2026-03-20T17:30:23.207919"
  },
  {
    "url": "https://wwwterminal.sctech.qzz.io",
    "status": "up",
    "timestamp": "2026-03-20T17:30:28.895444"
  },
  {
    "url": "https://nnn.n.nu",
    "status": "down",
    "timestamp": "2026-03-20T17:30:29.308836"
  }
]