[
  {
    "url": "https://sctech.localplayer.dev",
    "status": "up",
    "timestamp": "2025-10-04T23:33:37.573890"
  },
  {
    "url": "https://blog.sctech.localplayer.dev",
    "status": "up",
    "timestamp": "2025-10-04T23:33:37.788330"
  },
  {
    "url": "https://docs.sctech.localplayer.dev",
    "status": "up",
    "timestamp": "2025-10-04T23:33:38.179624"
  },
  {
    "url": "https://go.sctech.localplayer.dev",
    "status": "up",
    "timestamp": "2025-10-04T23:33:38.698740"
  },
  {
    "url": "https://cndl.web.app",
    "status": "up",
    "timestamp": "2025-10-04T23:33:38.752211"
  },
  {
    "url": "https://osearch.app.sctech.localplayer.dev",
    "status": "up",
    "timestamp": "2025-10-04T23:33:38.870692"
  },
  {
    "url": "https://lolchat.app.sctech.localplayer.dev",
    "status": "up",
    "timestamp": "2025-10-04T23:33:38.974887"
  },
  {
    "url": "https://go-md.app.sctech.localplayer.dev",
    "status": "up",
    "timestamp": "2025-10-04T23:33:39.079991"
  },
  {
    "url": "https://breadblog.app.sctech.localplayer.dev",
    "status": "up",
    "timestamp": "2025-10-04T23:33:39.198141"
  },
  {
    "url": "https://wwwterminal.app.sctech.localplayer.dev",
    "status": "up",
    "timestamp": "2025-10-04T23:33:39.933347"
  },
  {
    "url": "https://nnn.n.nu",
    "status": "up",
    "timestamp": "2025-10-04T23:33:40.450976"
  }
]