[
  {
    "url": "https://sctech.qzz.io",
    "status": "up",
    "timestamp": "2026-01-18T18:51:58.502887"
  },
  {
    "url": "https://blog.sctech.qzz.io",
    "status": "up",
    "timestamp": "2026-01-18T18:51:58.662531"
  },
  {
    "url": "https://docs.sctech.qzz.io",
    "status": "up",
    "timestamp": "2026-01-18T18:51:58.979109"
  },
  {
    "url": "https://go.sctech.localplayer.dev",
    "status": "down",
    "timestamp": "2026-01-18T18:51:59.664573"
  },
  {
    "url": "https://cndl.web.app",
    "status": "up",
    "timestamp": "2026-01-18T18:51:59.812865"
  },
  {
    "url": "https://osearch.sctech.qzz.io",
    "status": "up",
    "timestamp": "2026-01-18T18:52:00.766906"
  },
  {
    "url": "https://lolchat.app.sctech.localplayer.dev",
    "status": "up",
    "timestamp": "2026-01-18T18:52:01.665508"
  },
  {
    "url": "https://markdown.sctech.qzz.io",
    "status": "up",
    "timestamp": "2026-01-18T18:52:02.496186"
  },
  {
    "url": "https://breadblog.sctech.qzz.io",
    "status": "up",
    "timestamp": "2026-01-18T18:52:02.630416"
  },
  {
    "url": "https://wwwterminal.sctech.qzz.io",
    "status": "up",
    "timestamp": "2026-01-18T18:52:03.402259"
  },
  {
    "url": "https://nnn.n.nu",
    "status": "down",
    "timestamp": "2026-01-18T18:52:03.911974"
  }
]