[
  {
    "url": "https://sctech.qzz.io",
    "status": "up",
    "timestamp": "2025-11-20T15:55:55.763766"
  },
  {
    "url": "https://blog.sctech.qzz.io",
    "status": "up",
    "timestamp": "2025-11-20T15:55:56.233329"
  },
  {
    "url": "https://docs.sctech.qzz.io",
    "status": "up",
    "timestamp": "2025-11-20T15:56:01.021883"
  },
  {
    "url": "https://go.sctech.localplayer.dev",
    "status": "up",
    "timestamp": "2025-11-20T15:56:01.311945"
  },
  {
    "url": "https://cndl.web.app",
    "status": "up",
    "timestamp": "2025-11-20T15:56:01.405483"
  },
  {
    "url": "https://osearch.sctech.qzz.io",
    "status": "up",
    "timestamp": "2025-11-20T15:56:01.647974"
  },
  {
    "url": "https://lolchat.app.sctech.localplayer.dev",
    "status": "up",
    "timestamp": "2025-11-20T15:56:01.798336"
  },
  {
    "url": "https://markdown.sctech.qzz.io",
    "status": "up",
    "timestamp": "2025-11-20T15:56:10.433944"
  },
  {
    "url": "https://breadblog.sctech.qzz.io",
    "status": "up",
    "timestamp": "2025-11-20T15:56:14.671304"
  },
  {
    "url": "https://wwwterminal.sctech.qzz.io",
    "status": "up",
    "timestamp": "2025-11-20T15:56:15.311025"
  },
  {
    "url": "https://nnn.n.nu",
    "status": "down",
    "timestamp": "2025-11-20T15:56:15.776412"
  }
]