[
  {
    "url": "https://sctech.qzz.io",
    "status": "up",
    "timestamp": "2026-02-20T09:42:02.832441"
  },
  {
    "url": "https://blog.sctech.qzz.io",
    "status": "up",
    "timestamp": "2026-02-20T09:42:03.007866"
  },
  {
    "url": "https://docs.sctech.qzz.io",
    "status": "up",
    "timestamp": "2026-02-20T09:42:07.529722"
  },
  {
    "url": "https://go.sctech.localplayer.dev",
    "status": "down",
    "timestamp": "2026-02-20T09:42:07.975637"
  },
  {
    "url": "https://cndl.web.app",
    "status": "up",
    "timestamp": "2026-02-20T09:42:08.082209"
  },
  {
    "url": "https://osearch.sctech.qzz.io",
    "status": "up",
    "timestamp": "2026-02-20T09:42:08.749833"
  },
  {
    "url": "https://lolchat.app.sctech.localplayer.dev",
    "status": "up",
    "timestamp": "2026-02-20T09:42:08.820281"
  },
  {
    "url": "https://markdown.sctech.qzz.io",
    "status": "up",
    "timestamp": "2026-02-20T09:42:09.225078"
  },
  {
    "url": "https://breadblog.sctech.qzz.io",
    "status": "up",
    "timestamp": "2026-02-20T09:42:09.842907"
  },
  {
    "url": "https://wwwterminal.sctech.qzz.io",
    "status": "up",
    "timestamp": "2026-02-20T09:42:10.009456"
  },
  {
    "url": "https://nnn.n.nu",
    "status": "down",
    "timestamp": "2026-02-20T09:42:10.307166"
  }
]