[
  {
    "url": "https://sctech.qzz.io",
    "status": "up",
    "timestamp": "2026-01-17T22:36:30.021202"
  },
  {
    "url": "https://blog.sctech.qzz.io",
    "status": "up",
    "timestamp": "2026-01-17T22:36:35.273376"
  },
  {
    "url": "https://docs.sctech.qzz.io",
    "status": "up",
    "timestamp": "2026-01-17T22:36:40.076270"
  },
  {
    "url": "https://go.sctech.localplayer.dev",
    "status": "down",
    "timestamp": "2026-01-17T22:36:40.832845"
  },
  {
    "url": "https://cndl.web.app",
    "status": "up",
    "timestamp": "2026-01-17T22:36:40.958803"
  },
  {
    "url": "https://osearch.sctech.qzz.io",
    "status": "up",
    "timestamp": "2026-01-17T22:36:41.310637"
  },
  {
    "url": "https://lolchat.app.sctech.localplayer.dev",
    "status": "up",
    "timestamp": "2026-01-17T22:36:42.230292"
  },
  {
    "url": "https://markdown.sctech.qzz.io",
    "status": "up",
    "timestamp": "2026-01-17T22:36:42.722252"
  },
  {
    "url": "https://breadblog.sctech.qzz.io",
    "status": "up",
    "timestamp": "2026-01-17T22:36:43.485947"
  },
  {
    "url": "https://wwwterminal.sctech.qzz.io",
    "status": "up",
    "timestamp": "2026-01-17T22:36:43.953796"
  },
  {
    "url": "https://nnn.n.nu",
    "status": "down",
    "timestamp": "2026-01-17T22:36:44.526840"
  }
]