[
  {
    "url": "https://sctech.qzz.io",
    "status": "up",
    "timestamp": "2026-02-14T07:01:57.826732"
  },
  {
    "url": "https://blog.sctech.qzz.io",
    "status": "up",
    "timestamp": "2026-02-14T07:01:58.204257"
  },
  {
    "url": "https://docs.sctech.qzz.io",
    "status": "up",
    "timestamp": "2026-02-14T07:01:58.490671"
  },
  {
    "url": "https://go.sctech.localplayer.dev",
    "status": "down",
    "timestamp": "2026-02-14T07:01:59.005460"
  },
  {
    "url": "https://cndl.web.app",
    "status": "up",
    "timestamp": "2026-02-14T07:01:59.119082"
  },
  {
    "url": "https://osearch.sctech.qzz.io",
    "status": "up",
    "timestamp": "2026-02-14T07:02:03.720597"
  },
  {
    "url": "https://lolchat.app.sctech.localplayer.dev",
    "status": "up",
    "timestamp": "2026-02-14T07:02:03.977268"
  },
  {
    "url": "https://markdown.sctech.qzz.io",
    "status": "up",
    "timestamp": "2026-02-14T07:02:04.188737"
  },
  {
    "url": "https://breadblog.sctech.qzz.io",
    "status": "up",
    "timestamp": "2026-02-14T07:02:04.846941"
  },
  {
    "url": "https://wwwterminal.sctech.qzz.io",
    "status": "up",
    "timestamp": "2026-02-14T07:02:05.022719"
  },
  {
    "url": "https://nnn.n.nu",
    "status": "down",
    "timestamp": "2026-02-14T07:02:05.449879"
  }
]