[
  {
    "url": "https://sctech.localplayer.dev",
    "status": "up",
    "timestamp": "2025-10-13T08:47:43.800400"
  },
  {
    "url": "https://blog.sctech.localplayer.dev",
    "status": "down",
    "timestamp": "2025-10-13T08:47:43.880542"
  },
  {
    "url": "https://docs.sctech.localplayer.dev",
    "status": "up",
    "timestamp": "2025-10-13T08:47:44.357607"
  },
  {
    "url": "https://go.sctech.localplayer.dev",
    "status": "up",
    "timestamp": "2025-10-13T08:47:44.878683"
  },
  {
    "url": "https://cndl.web.app",
    "status": "up",
    "timestamp": "2025-10-13T08:47:45.026873"
  },
  {
    "url": "https://osearch.app.sctech.localplayer.dev",
    "status": "up",
    "timestamp": "2025-10-13T08:47:45.558794"
  },
  {
    "url": "https://lolchat.app.sctech.localplayer.dev",
    "status": "up",
    "timestamp": "2025-10-13T08:47:46.044150"
  },
  {
    "url": "https://go-md.app.sctech.localplayer.dev",
    "status": "up",
    "timestamp": "2025-10-13T08:47:46.141746"
  },
  {
    "url": "https://breadblog.app.sctech.localplayer.dev",
    "status": "up",
    "timestamp": "2025-10-13T08:47:46.404265"
  },
  {
    "url": "https://wwwterminal.app.sctech.localplayer.dev",
    "status": "up",
    "timestamp": "2025-10-13T08:47:46.560171"
  },
  {
    "url": "https://nnn.n.nu",
    "status": "up",
    "timestamp": "2025-10-13T08:47:46.910157"
  }
]