[
  {
    "url": "https://sctech.localplayer.dev",
    "status": "up",
    "timestamp": "2025-10-13T20:55:16.093060"
  },
  {
    "url": "https://blog.sctech.localplayer.dev",
    "status": "down",
    "timestamp": "2025-10-13T20:55:16.156366"
  },
  {
    "url": "https://docs.sctech.localplayer.dev",
    "status": "down",
    "timestamp": "2025-10-13T20:55:16.295692"
  },
  {
    "url": "https://go.sctech.localplayer.dev",
    "status": "up",
    "timestamp": "2025-10-13T20:55:16.755225"
  },
  {
    "url": "https://cndl.web.app",
    "status": "up",
    "timestamp": "2025-10-13T20:55:16.861806"
  },
  {
    "url": "https://osearch.app.sctech.localplayer.dev",
    "status": "up",
    "timestamp": "2025-10-13T20:55:17.332754"
  },
  {
    "url": "https://lolchat.app.sctech.localplayer.dev",
    "status": "up",
    "timestamp": "2025-10-13T20:55:17.775742"
  },
  {
    "url": "https://go-md.app.sctech.localplayer.dev",
    "status": "up",
    "timestamp": "2025-10-13T20:55:17.955885"
  },
  {
    "url": "https://breadblog.app.sctech.localplayer.dev",
    "status": "up",
    "timestamp": "2025-10-13T20:55:18.506793"
  },
  {
    "url": "https://wwwterminal.app.sctech.localplayer.dev",
    "status": "up",
    "timestamp": "2025-10-13T20:55:19.091172"
  },
  {
    "url": "https://nnn.n.nu",
    "status": "up",
    "timestamp": "2025-10-13T20:55:19.643541"
  }
]