[
  {
    "url": "https://sctech.qzz.io",
    "status": "up",
    "timestamp": "2026-01-14T11:46:12.802058"
  },
  {
    "url": "https://blog.sctech.qzz.io",
    "status": "up",
    "timestamp": "2026-01-14T11:46:21.481181"
  },
  {
    "url": "https://docs.sctech.qzz.io",
    "status": "up",
    "timestamp": "2026-01-14T11:46:21.922513"
  },
  {
    "url": "https://go.sctech.localplayer.dev",
    "status": "down",
    "timestamp": "2026-01-14T11:46:22.286310"
  },
  {
    "url": "https://cndl.web.app",
    "status": "up",
    "timestamp": "2026-01-14T11:46:22.377452"
  },
  {
    "url": "https://osearch.sctech.qzz.io",
    "status": "up",
    "timestamp": "2026-01-14T11:46:30.686163"
  },
  {
    "url": "https://lolchat.app.sctech.localplayer.dev",
    "status": "up",
    "timestamp": "2026-01-14T11:46:31.420204"
  },
  {
    "url": "https://markdown.sctech.qzz.io",
    "status": "up",
    "timestamp": "2026-01-14T11:46:36.661314"
  },
  {
    "url": "https://breadblog.sctech.qzz.io",
    "status": "up",
    "timestamp": "2026-01-14T11:46:44.631359"
  },
  {
    "url": "https://wwwterminal.sctech.qzz.io",
    "status": "up",
    "timestamp": "2026-01-14T11:46:48.913215"
  },
  {
    "url": "https://nnn.n.nu",
    "status": "down",
    "timestamp": "2026-01-14T11:46:49.167693"
  }
]