[
  {
    "url": "https://sctech.qzz.io",
    "status": "up",
    "timestamp": "2025-12-01T14:22:36.213683"
  },
  {
    "url": "https://blog.sctech.qzz.io",
    "status": "up",
    "timestamp": "2025-12-01T14:22:36.690999"
  },
  {
    "url": "https://docs.sctech.qzz.io",
    "status": "up",
    "timestamp": "2025-12-01T14:22:37.300538"
  },
  {
    "url": "https://go.sctech.localplayer.dev",
    "status": "up",
    "timestamp": "2025-12-01T14:22:38.020974"
  },
  {
    "url": "https://cndl.web.app",
    "status": "up",
    "timestamp": "2025-12-01T14:22:38.147221"
  },
  {
    "url": "https://osearch.sctech.qzz.io",
    "status": "up",
    "timestamp": "2025-12-01T14:22:42.385721"
  },
  {
    "url": "https://lolchat.app.sctech.localplayer.dev",
    "status": "up",
    "timestamp": "2025-12-01T14:22:42.878284"
  },
  {
    "url": "https://markdown.sctech.qzz.io",
    "status": "up",
    "timestamp": "2025-12-01T14:22:43.178781"
  },
  {
    "url": "https://breadblog.sctech.qzz.io",
    "status": "up",
    "timestamp": "2025-12-01T14:22:43.314567"
  },
  {
    "url": "https://wwwterminal.sctech.qzz.io",
    "status": "up",
    "timestamp": "2025-12-01T14:22:48.243048"
  },
  {
    "url": "https://nnn.n.nu",
    "status": "down",
    "timestamp": "2025-12-01T14:22:48.535168"
  }
]