[
  {
    "url": "https://sctech.qzz.io",
    "status": "up",
    "timestamp": "2025-11-30T08:47:59.550643"
  },
  {
    "url": "https://blog.sctech.qzz.io",
    "status": "up",
    "timestamp": "2025-11-30T08:48:04.108635"
  },
  {
    "url": "https://docs.sctech.qzz.io",
    "status": "up",
    "timestamp": "2025-11-30T08:48:07.502602"
  },
  {
    "url": "https://go.sctech.localplayer.dev",
    "status": "up",
    "timestamp": "2025-11-30T08:48:08.197604"
  },
  {
    "url": "https://cndl.web.app",
    "status": "up",
    "timestamp": "2025-11-30T08:48:08.377143"
  },
  {
    "url": "https://osearch.sctech.qzz.io",
    "status": "up",
    "timestamp": "2025-11-30T08:48:09.112920"
  },
  {
    "url": "https://lolchat.app.sctech.localplayer.dev",
    "status": "up",
    "timestamp": "2025-11-30T08:48:09.713242"
  },
  {
    "url": "https://markdown.sctech.qzz.io",
    "status": "up",
    "timestamp": "2025-11-30T08:48:15.114175"
  },
  {
    "url": "https://breadblog.sctech.qzz.io",
    "status": "up",
    "timestamp": "2025-11-30T08:48:15.408606"
  },
  {
    "url": "https://wwwterminal.sctech.qzz.io",
    "status": "up",
    "timestamp": "2025-11-30T08:48:15.538330"
  },
  {
    "url": "https://nnn.n.nu",
    "status": "down",
    "timestamp": "2025-11-30T08:48:16.143244"
  }
]