[
  {
    "url": "https://sctech.qzz.io",
    "status": "up",
    "timestamp": "2025-11-13T21:51:59.468766"
  },
  {
    "url": "https://blog.sctech.qzz.io",
    "status": "up",
    "timestamp": "2025-11-13T21:51:59.746655"
  },
  {
    "url": "https://docs.sctech.qzz.io",
    "status": "up",
    "timestamp": "2025-11-13T21:52:00.237704"
  },
  {
    "url": "https://go.sctech.localplayer.dev",
    "status": "up",
    "timestamp": "2025-11-13T21:52:00.820353"
  },
  {
    "url": "https://cndl.web.app",
    "status": "up",
    "timestamp": "2025-11-13T21:52:00.932762"
  },
  {
    "url": "https://osearch.sctech.qzz.io",
    "status": "up",
    "timestamp": "2025-11-13T21:52:01.247359"
  },
  {
    "url": "https://lolchat.app.sctech.localplayer.dev",
    "status": "up",
    "timestamp": "2025-11-13T21:52:01.336144"
  },
  {
    "url": "https://markdown.sctech.qzz.io",
    "status": "up",
    "timestamp": "2025-11-13T21:52:01.889518"
  },
  {
    "url": "https://breadblog.sctech.qzz.io",
    "status": "up",
    "timestamp": "2025-11-13T21:52:02.185858"
  },
  {
    "url": "https://wwwterminal.sctech.qzz.io",
    "status": "up",
    "timestamp": "2025-11-13T21:52:06.377396"
  },
  {
    "url": "https://nnn.n.nu",
    "status": "down",
    "timestamp": "2025-11-13T21:52:06.670900"
  }
]