[
  {
    "url": "https://sctech.qzz.io",
    "status": "up",
    "timestamp": "2025-12-14T06:51:47.054519"
  },
  {
    "url": "https://blog.sctech.qzz.io",
    "status": "up",
    "timestamp": "2025-12-14T06:51:47.466318"
  },
  {
    "url": "https://docs.sctech.qzz.io",
    "status": "up",
    "timestamp": "2025-12-14T06:51:48.035145"
  },
  {
    "url": "https://go.sctech.localplayer.dev",
    "status": "up",
    "timestamp": "2025-12-14T06:51:48.943524"
  },
  {
    "url": "https://cndl.web.app",
    "status": "up",
    "timestamp": "2025-12-14T06:51:49.205241"
  },
  {
    "url": "https://osearch.sctech.qzz.io",
    "status": "up",
    "timestamp": "2025-12-14T06:51:49.790211"
  },
  {
    "url": "https://lolchat.app.sctech.localplayer.dev",
    "status": "up",
    "timestamp": "2025-12-14T06:51:50.344035"
  },
  {
    "url": "https://markdown.sctech.qzz.io",
    "status": "up",
    "timestamp": "2025-12-14T06:51:50.580567"
  },
  {
    "url": "https://breadblog.sctech.qzz.io",
    "status": "up",
    "timestamp": "2025-12-14T06:51:51.044458"
  },
  {
    "url": "https://wwwterminal.sctech.qzz.io",
    "status": "up",
    "timestamp": "2025-12-14T06:51:51.685336"
  },
  {
    "url": "https://nnn.n.nu",
    "status": "down",
    "timestamp": "2025-12-14T06:51:52.272003"
  }
]