[
  {
    "url": "https://sctech.qzz.io",
    "status": "up",
    "timestamp": "2026-02-11T18:33:54.487953"
  },
  {
    "url": "https://blog.sctech.qzz.io",
    "status": "up",
    "timestamp": "2026-02-11T18:33:54.825218"
  },
  {
    "url": "https://docs.sctech.qzz.io",
    "status": "up",
    "timestamp": "2026-02-11T18:33:55.299054"
  },
  {
    "url": "https://go.sctech.localplayer.dev",
    "status": "down",
    "timestamp": "2026-02-11T18:33:55.639731"
  },
  {
    "url": "https://cndl.web.app",
    "status": "up",
    "timestamp": "2026-02-11T18:33:55.781984"
  },
  {
    "url": "https://osearch.sctech.qzz.io",
    "status": "up",
    "timestamp": "2026-02-11T18:34:01.584808"
  },
  {
    "url": "https://lolchat.app.sctech.localplayer.dev",
    "status": "up",
    "timestamp": "2026-02-11T18:34:02.173918"
  },
  {
    "url": "https://markdown.sctech.qzz.io",
    "status": "up",
    "timestamp": "2026-02-11T18:34:06.846829"
  },
  {
    "url": "https://breadblog.sctech.qzz.io",
    "status": "up",
    "timestamp": "2026-02-11T18:34:07.740044"
  },
  {
    "url": "https://wwwterminal.sctech.qzz.io",
    "status": "up",
    "timestamp": "2026-02-11T18:34:08.526447"
  },
  {
    "url": "https://nnn.n.nu",
    "status": "down",
    "timestamp": "2026-02-11T18:34:09.001449"
  }
]