[
  {
    "url": "https://sctech.qzz.io",
    "status": "up",
    "timestamp": "2025-11-29T23:28:44.207558"
  },
  {
    "url": "https://blog.sctech.qzz.io",
    "status": "up",
    "timestamp": "2025-11-29T23:28:49.547324"
  },
  {
    "url": "https://docs.sctech.qzz.io",
    "status": "up",
    "timestamp": "2025-11-29T23:29:02.153415"
  },
  {
    "url": "https://go.sctech.localplayer.dev",
    "status": "up",
    "timestamp": "2025-11-29T23:29:02.663222"
  },
  {
    "url": "https://cndl.web.app",
    "status": "up",
    "timestamp": "2025-11-29T23:29:02.774235"
  },
  {
    "url": "https://osearch.sctech.qzz.io",
    "status": "up",
    "timestamp": "2025-11-29T23:29:07.914895"
  },
  {
    "url": "https://lolchat.app.sctech.localplayer.dev",
    "status": "up",
    "timestamp": "2025-11-29T23:29:08.017898"
  },
  {
    "url": "https://markdown.sctech.qzz.io",
    "status": "up",
    "timestamp": "2025-11-29T23:29:13.136812"
  },
  {
    "url": "https://breadblog.sctech.qzz.io",
    "status": "up",
    "timestamp": "2025-11-29T23:29:13.628248"
  },
  {
    "url": "https://wwwterminal.sctech.qzz.io",
    "status": "up",
    "timestamp": "2025-11-29T23:29:13.939521"
  },
  {
    "url": "https://nnn.n.nu",
    "status": "down",
    "timestamp": "2025-11-29T23:29:14.398703"
  }
]