[
  {
    "url": "https://sctech.qzz.io",
    "status": "up",
    "timestamp": "2026-04-06T10:50:32.100151"
  },
  {
    "url": "https://blog.sctech.qzz.io",
    "status": "up",
    "timestamp": "2026-04-06T10:50:32.311590"
  },
  {
    "url": "https://docs.sctech.qzz.io",
    "status": "up",
    "timestamp": "2026-04-06T10:50:32.684428"
  },
  {
    "url": "https://go.sctech.localplayer.dev",
    "status": "down",
    "timestamp": "2026-04-06T10:50:33.162020"
  },
  {
    "url": "https://cndl.web.app",
    "status": "up",
    "timestamp": "2026-04-06T10:50:33.302455"
  },
  {
    "url": "https://osearch.sctech.qzz.io",
    "status": "up",
    "timestamp": "2026-04-06T10:50:33.967114"
  },
  {
    "url": "https://lolchat.app.sctech.localplayer.dev",
    "status": "up",
    "timestamp": "2026-04-06T10:50:34.876862"
  },
  {
    "url": "https://markdown.sctech.qzz.io",
    "status": "up",
    "timestamp": "2026-04-06T10:50:35.488364"
  },
  {
    "url": "https://breadblog.sctech.qzz.io",
    "status": "up",
    "timestamp": "2026-04-06T10:50:36.136993"
  },
  {
    "url": "https://wwwterminal.sctech.qzz.io",
    "status": "up",
    "timestamp": "2026-04-06T10:50:40.780180"
  },
  {
    "url": "https://nnn.n.nu",
    "status": "down",
    "timestamp": "2026-04-06T10:50:41.068134"
  }
]