[
  {
    "url": "https://sctech.qzz.io",
    "status": "up",
    "timestamp": "2026-02-14T07:59:33.794374"
  },
  {
    "url": "https://blog.sctech.qzz.io",
    "status": "up",
    "timestamp": "2026-02-14T07:59:34.008257"
  },
  {
    "url": "https://docs.sctech.qzz.io",
    "status": "up",
    "timestamp": "2026-02-14T07:59:34.301733"
  },
  {
    "url": "https://go.sctech.localplayer.dev",
    "status": "down",
    "timestamp": "2026-02-14T07:59:34.945333"
  },
  {
    "url": "https://cndl.web.app",
    "status": "up",
    "timestamp": "2026-02-14T07:59:35.079786"
  },
  {
    "url": "https://osearch.sctech.qzz.io",
    "status": "up",
    "timestamp": "2026-02-14T07:59:35.627492"
  },
  {
    "url": "https://lolchat.app.sctech.localplayer.dev",
    "status": "up",
    "timestamp": "2026-02-14T07:59:35.837027"
  },
  {
    "url": "https://markdown.sctech.qzz.io",
    "status": "up",
    "timestamp": "2026-02-14T07:59:36.988988"
  },
  {
    "url": "https://breadblog.sctech.qzz.io",
    "status": "up",
    "timestamp": "2026-02-14T07:59:37.624874"
  },
  {
    "url": "https://wwwterminal.sctech.qzz.io",
    "status": "up",
    "timestamp": "2026-02-14T07:59:37.948066"
  },
  {
    "url": "https://nnn.n.nu",
    "status": "down",
    "timestamp": "2026-02-14T07:59:38.379381"
  }
]