[
  {
    "url": "https://sctech.qzz.io",
    "status": "up",
    "timestamp": "2026-03-30T10:43:23.267826"
  },
  {
    "url": "https://blog.sctech.qzz.io",
    "status": "up",
    "timestamp": "2026-03-30T10:43:27.805209"
  },
  {
    "url": "https://docs.sctech.qzz.io",
    "status": "up",
    "timestamp": "2026-03-30T10:43:28.286299"
  },
  {
    "url": "https://go.sctech.localplayer.dev",
    "status": "down",
    "timestamp": "2026-03-30T10:43:28.680194"
  },
  {
    "url": "https://cndl.web.app",
    "status": "up",
    "timestamp": "2026-03-30T10:43:28.815182"
  },
  {
    "url": "https://osearch.sctech.qzz.io",
    "status": "up",
    "timestamp": "2026-03-30T10:43:34.902761"
  },
  {
    "url": "https://lolchat.app.sctech.localplayer.dev",
    "status": "up",
    "timestamp": "2026-03-30T10:43:35.471267"
  },
  {
    "url": "https://markdown.sctech.qzz.io",
    "status": "up",
    "timestamp": "2026-03-30T10:43:35.706152"
  },
  {
    "url": "https://breadblog.sctech.qzz.io",
    "status": "up",
    "timestamp": "2026-03-30T10:43:36.183038"
  },
  {
    "url": "https://wwwterminal.sctech.qzz.io",
    "status": "up",
    "timestamp": "2026-03-30T10:43:36.824241"
  },
  {
    "url": "https://nnn.n.nu",
    "status": "down",
    "timestamp": "2026-03-30T10:43:37.220807"
  }
]