[
  {
    "url": "https://sctech.qzz.io",
    "status": "up",
    "timestamp": "2026-03-15T21:37:19.479919"
  },
  {
    "url": "https://blog.sctech.qzz.io",
    "status": "up",
    "timestamp": "2026-03-15T21:37:19.797298"
  },
  {
    "url": "https://docs.sctech.qzz.io",
    "status": "up",
    "timestamp": "2026-03-15T21:37:20.066063"
  },
  {
    "url": "https://go.sctech.localplayer.dev",
    "status": "down",
    "timestamp": "2026-03-15T21:37:20.498489"
  },
  {
    "url": "https://cndl.web.app",
    "status": "up",
    "timestamp": "2026-03-15T21:37:20.785564"
  },
  {
    "url": "https://osearch.sctech.qzz.io",
    "status": "up",
    "timestamp": "2026-03-15T21:37:27.176123"
  },
  {
    "url": "https://lolchat.app.sctech.localplayer.dev",
    "status": "up",
    "timestamp": "2026-03-15T21:37:27.741356"
  },
  {
    "url": "https://markdown.sctech.qzz.io",
    "status": "up",
    "timestamp": "2026-03-15T21:37:34.226433"
  },
  {
    "url": "https://breadblog.sctech.qzz.io",
    "status": "up",
    "timestamp": "2026-03-15T21:37:38.501377"
  },
  {
    "url": "https://wwwterminal.sctech.qzz.io",
    "status": "up",
    "timestamp": "2026-03-15T21:37:44.157696"
  },
  {
    "url": "https://nnn.n.nu",
    "status": "down",
    "timestamp": "2026-03-15T21:37:44.557418"
  }
]