[
  {
    "url": "https://sctech.localplayer.dev",
    "status": "up",
    "timestamp": "2025-10-08T04:49:09.165045"
  },
  {
    "url": "https://blog.sctech.localplayer.dev",
    "status": "up",
    "timestamp": "2025-10-08T04:49:09.413555"
  },
  {
    "url": "https://docs.sctech.localplayer.dev",
    "status": "up",
    "timestamp": "2025-10-08T04:49:09.924714"
  },
  {
    "url": "https://go.sctech.localplayer.dev",
    "status": "up",
    "timestamp": "2025-10-08T04:49:10.502071"
  },
  {
    "url": "https://cndl.web.app",
    "status": "up",
    "timestamp": "2025-10-08T04:49:10.662556"
  },
  {
    "url": "https://osearch.app.sctech.localplayer.dev",
    "status": "up",
    "timestamp": "2025-10-08T04:49:10.786693"
  },
  {
    "url": "https://lolchat.app.sctech.localplayer.dev",
    "status": "up",
    "timestamp": "2025-10-08T04:49:10.965234"
  },
  {
    "url": "https://go-md.app.sctech.localplayer.dev",
    "status": "up",
    "timestamp": "2025-10-08T04:49:11.408666"
  },
  {
    "url": "https://breadblog.app.sctech.localplayer.dev",
    "status": "up",
    "timestamp": "2025-10-08T04:49:11.864316"
  },
  {
    "url": "https://wwwterminal.app.sctech.localplayer.dev",
    "status": "up",
    "timestamp": "2025-10-08T04:49:12.063054"
  },
  {
    "url": "https://nnn.n.nu",
    "status": "up",
    "timestamp": "2025-10-08T04:49:12.450794"
  }
]