[
  {
    "url": "https://sctech.qzz.io",
    "status": "up",
    "timestamp": "2026-02-14T09:15:01.405191"
  },
  {
    "url": "https://blog.sctech.qzz.io",
    "status": "up",
    "timestamp": "2026-02-14T09:15:05.284025"
  },
  {
    "url": "https://docs.sctech.qzz.io",
    "status": "up",
    "timestamp": "2026-02-14T09:15:09.872079"
  },
  {
    "url": "https://go.sctech.localplayer.dev",
    "status": "down",
    "timestamp": "2026-02-14T09:15:10.283185"
  },
  {
    "url": "https://cndl.web.app",
    "status": "up",
    "timestamp": "2026-02-14T09:15:10.384772"
  },
  {
    "url": "https://osearch.sctech.qzz.io",
    "status": "up",
    "timestamp": "2026-02-14T09:15:19.291608"
  },
  {
    "url": "https://lolchat.app.sctech.localplayer.dev",
    "status": "up",
    "timestamp": "2026-02-14T09:15:19.891751"
  },
  {
    "url": "https://markdown.sctech.qzz.io",
    "status": "up",
    "timestamp": "2026-02-14T09:15:20.474797"
  },
  {
    "url": "https://breadblog.sctech.qzz.io",
    "status": "up",
    "timestamp": "2026-02-14T09:15:30.857463"
  },
  {
    "url": "https://wwwterminal.sctech.qzz.io",
    "status": "up",
    "timestamp": "2026-02-14T09:15:35.957418"
  },
  {
    "url": "https://nnn.n.nu",
    "status": "down",
    "timestamp": "2026-02-14T09:15:36.300910"
  }
]