[
  {
    "url": "https://sctech.qzz.io",
    "status": "up",
    "timestamp": "2025-12-22T23:11:27.314989"
  },
  {
    "url": "https://blog.sctech.qzz.io",
    "status": "up",
    "timestamp": "2025-12-22T23:11:31.217182"
  },
  {
    "url": "https://docs.sctech.qzz.io",
    "status": "up",
    "timestamp": "2025-12-22T23:11:45.262982"
  },
  {
    "url": "https://go.sctech.localplayer.dev",
    "status": "down",
    "timestamp": "2025-12-22T23:11:46.143082"
  },
  {
    "url": "https://cndl.web.app",
    "status": "up",
    "timestamp": "2025-12-22T23:11:46.259737"
  },
  {
    "url": "https://osearch.sctech.qzz.io",
    "status": "up",
    "timestamp": "2025-12-22T23:11:51.262624"
  },
  {
    "url": "https://lolchat.app.sctech.localplayer.dev",
    "status": "up",
    "timestamp": "2025-12-22T23:11:51.955646"
  },
  {
    "url": "https://markdown.sctech.qzz.io",
    "status": "up",
    "timestamp": "2025-12-22T23:11:52.182837"
  },
  {
    "url": "https://breadblog.sctech.qzz.io",
    "status": "up",
    "timestamp": "2025-12-22T23:11:52.810380"
  },
  {
    "url": "https://wwwterminal.sctech.qzz.io",
    "status": "up",
    "timestamp": "2025-12-22T23:11:57.628813"
  },
  {
    "url": "https://nnn.n.nu",
    "status": "down",
    "timestamp": "2025-12-22T23:11:58.514360"
  }
]